metasub_utils.hudson_alpha-0.3.1-py3.6-nspkg.pth
metasub_utils/hudson_alpha/__init__.py
metasub_utils/hudson_alpha/cli.py
metasub_utils/hudson_alpha/constants.py
metasub_utils/hudson_alpha/hudson_alpha.py
metasub_utils/hudson_alpha/hudson_alpha_flowcells.csv
metasub_utils/hudson_alpha/migrate.py
metasub_utils/hudson_alpha/utils.py
metasub_utils.hudson_alpha-0.3.1.dist-info/METADATA
metasub_utils.hudson_alpha-0.3.1.dist-info/WHEEL
metasub_utils.hudson_alpha-0.3.1.dist-info/namespace_packages.txt
metasub_utils.hudson_alpha-0.3.1.dist-info/top_level.txt
metasub_utils.hudson_alpha-0.3.1.dist-info/RECORD
